gistmaker/gistmaker.py
gistmaker-1.0.0.dist-info/METADATA
gistmaker-1.0.0.dist-info/RECORD
gistmaker-1.0.0.dist-info/WHEEL
gistmaker-1.0.0.dist-info/top_level.txt
